word_template_engine/__init__.py
word_template_engine/setup.py
word_template_engine/word_template_engine.py
word_template_engine/utils/__init__.py
word_template_engine/utils/common.py
word_template_engine/utils/image_processor.py
word_template_engine/utils/table_processor.py
word_template_engine/utils/text_processor.py
word_template_engine-0.3.0.dist-info/METADATA
word_template_engine-0.3.0.dist-info/WHEEL
word_template_engine-0.3.0.dist-info/top_level.txt
word_template_engine-0.3.0.dist-info/RECORD
