Metadata-Version: 2.4
Name: word-template-engine
Version: 0.3.0
Summary: A python of Word template engine,一个支持根据word模板生成word文档的docx引擎
Home-page: https://github.com/sixsfish/word_template_engine
Author: sixsfish
Author-email: sixsfish <sixsfish@foxmail.com>
License: MIT
Project-URL: Homepage, https://github.com/sixsfish/word_template_engine
Project-URL: Repository, https://github.com/sixsfish/word_template_engine
Classifier: Programming Language :: Python :: 3
Classifier: Programming Language :: Python :: 3.12
Classifier: License :: OSI Approved :: MIT License
Classifier: Operating System :: OS Independent
Classifier: Topic :: Office/Business :: Office Suites
Classifier: Topic :: Text Processing :: Markup
Requires-Python: >=3.12
Requires-Dist: lxml>=6.0.2
Requires-Dist: python-docx>=1.2.0
Requires-Dist: requests>=2.32.5
Dynamic: author
Dynamic: home-page
Dynamic: requires-python
